pytorch_tao/__init__.py
pytorch_tao/adversarial.py
pytorch_tao/args.py
pytorch_tao/cli.py
pytorch_tao/core.py
pytorch_tao/devtool.py
pytorch_tao/exceptions.py
pytorch_tao/helper.py
pytorch_tao/repo.py
pytorch_tao/trainer.py
pytorch_tao/tune.py
pytorch_tao/plugins/__init__.py
pytorch_tao/plugins/base.py
pytorch_tao/plugins/checkpoint.py
pytorch_tao/plugins/metrics.py
pytorch_tao/plugins/output_recorder.py
pytorch_tao/plugins/progress_bar.py
pytorch_tao/plugins/scheduler.py
pytorch_tao/templates/projects/cifar10/main.py.jinja
pytorch_tao/templates/projects/default/.gitignore.jinja
pytorch_tao/templates/projects/default/.tao/cfg.py.jinja
pytorch_tao/templates/projects/mini/main.py.jinja
pytorch_tao/templates/projects/mini/.tao/cfg.py.jinja
pytorch_tao/trackers/__init__.py
pytorch_tao/trackers/aim_tracker.py
pytorch_tao/trackers/base.py
pytorch_tao/trackers/neptune_tracker.py
pytorch_tao/trackers/wandb_tracker.py
pytorch_tao-0.1.10.dist-info/METADATA
pytorch_tao-0.1.10.dist-info/WHEEL
pytorch_tao-0.1.10.dist-info/entry_points.txt
pytorch_tao-0.1.10.dist-info/top_level.txt
pytorch_tao-0.1.10.dist-info/RECORD
