Metadata-Version: 2.1
Name: pytorch-tao
Version: 0.1.10
Summary: A toolbox for a specific Machine Learning training project
Home-page: https://github.com/louis-she/pytorch-tao
Author: Chenglu She
Author-email: chenglu.she@gmail.com
License: MIT
Requires-Python: >3.7
Requires-Dist: torch
Requires-Dist: GitPython ~=3.1.27
Requires-Dist: Jinja2 ~=3.1.2
Requires-Dist: kaggle ~=1.5.12
Requires-Dist: optuna ~=3.0.2
Requires-Dist: pytorch-ignite ~=0.4.10
Requires-Dist: filelock ~=3.8.0
